LICENSE
README.md
setup.cfg
setup.py
fastmap/__init__.py
fastmap/sdk_lib.py
fastmap.egg-info/PKG-INFO
fastmap.egg-info/SOURCES.txt
fastmap.egg-info/dependency_links.txt
fastmap.egg-info/requires.txt
fastmap.egg-info/top_level.txt
scripts/fastmap
scripts/fastmapadmin
tests/__init__.py
tests/test_sdk.py