Metadata-Version: 2.1
Name: fastmap
Version: 0.0.12
Summary: Fastmap offloads arbitrary Python code via the open source fastmap cloud service.
Home-page: https://github.com/fastmap-io/fastmap
Author: fastmap.io team
Author-email: scott@fastmap.io
License: UNKNOWN
Download-URL: https://github.com/fastmap-io/fastmap/archive/fastmap-0.0.12.tar.gz
Platform: UNKNOWN
Classifier: Programming Language :: Python :: 3
Classifier: License :: OSI Approved :: MIT License
Classifier: Operating System :: OS Independent
Requires-Python: >=3.7
